pymetheus/__init__.py
pymetheus/cli.py
pymetheus/pymetheus.py
pymetheus/logics/__init__.py
pymetheus/logics/fuzzy_logic.py
pymetheus/logics/interfaces.py
pymetheus/logics/lukasiewicz_logic.py
pymetheus/parser/__init__.py
pymetheus/parser/rule_parser.py
pymetheus/utils/__init__.py
pymetheus/utils/exceptions.py
pymetheus/utils/functionalities.py
pymetheus-0.3.1.dist-info/AUTHORS.rst
pymetheus-0.3.1.dist-info/LICENSE
pymetheus-0.3.1.dist-info/METADATA
pymetheus-0.3.1.dist-info/WHEEL
pymetheus-0.3.1.dist-info/entry_points.txt
pymetheus-0.3.1.dist-info/top_level.txt
pymetheus-0.3.1.dist-info/RECORD
