Metadata-Version: 2.1
Name: pymetheus
Version: 0.3.1
Summary: Logical Reasoning for Deep Nets
Home-page: https://github.com/vinid/pymetheus
Author: Federico Bianchi
Author-email: f.bianchi@unibocconi.it
License: GNU General Public License v3
Keywords: pymetheus
Platform: UNKNOWN
Classifier: Development Status :: 2 - Pre-Alpha
Classifier: Intended Audience :: Developers
Classifier: License :: OSI Approved :: GNU General Public License v3 (GPLv3)
Classifier: Natural Language :: English
Classifier: Programming Language :: Python :: 2
Classifier: Programming Language :: Python :: 2.7
Classifier: Programming Language :: Python :: 3
Classifier: Programming Language :: Python :: 3.4
Classifier: Programming Language :: Python :: 3.5
Classifier: Programming Language :: Python :: 3.6
Classifier: Programming Language :: Python :: 3.7
Requires-Dist: Sphinx (==1.8.1)
Requires-Dist: bumpversion (==0.5.3)
Requires-Dist: cloudpickle
Requires-Dist: coverage (==4.5.1)
Requires-Dist: flake8 (==3.5.0)
Requires-Dist: numpy
Requires-Dist: pip (==18.1)
Requires-Dist: pyparsing
Requires-Dist: pytest-runner (==4.2)
Requires-Dist: pytest (==3.8.2)
Requires-Dist: sklearn
Requires-Dist: torch
Requires-Dist: tox (==3.5.2)
Requires-Dist: tqdm
Requires-Dist: twine (==1.12.1)
Requires-Dist: watchdog (==0.9.0)
Requires-Dist: wheel (==0.32.1)
